commands/__init__.py
commands/lint.py
commands/utils/__init__.py
commands/utils/xcproj.py
swiftlint_runner-0.0.1.dist-info/LICENSE
swiftlint_runner-0.0.1.dist-info/LICENSE.md
swiftlint_runner-0.0.1.dist-info/METADATA
swiftlint_runner-0.0.1.dist-info/WHEEL
swiftlint_runner-0.0.1.dist-info/entry_points.txt
swiftlint_runner-0.0.1.dist-info/top_level.txt
swiftlint_runner-0.0.1.dist-info/RECORD
