Metadata-Version: 2.1
Name: swiftlint-runner
Version: 0.0.1
Summary: Missing SwiftLint runner with ability to define config file per target
Home-page: https://github.com/elpassion/swiftlint-runner
Author: Jakub Turek
Author-email: jakub.turek@elpassion.pl
License: MIT
Platform: UNKNOWN
Classifier: License :: OSI Approved :: MIT License
Classifier: Programming Language :: Python :: 3
Classifier: Programming Language :: Python :: 3.7
Requires-Dist: click
Requires-Dist: pyyaml
Requires-Dist: mod-pbxproj
